Metadata-Version: 1.0
Name: duel-distributions
Version: 0.1
Summary: Gaussian and Binomial distributions
Home-page: UNKNOWN
Author: Chen Zhao
Author-email: UNKNOWN
License: UNKNOWN
Platform: UNKNOWN
